nocturne/__init__.py
nocturne/api/__init__.py
nocturne/api/providers.py
nocturne/api/utils.py
nocturne/api/model_builder/__init__.py
nocturne/api/model_builder/base.py
nocturne/api/model_builder/tensorflow.py
nocturne-0.0.6.dist-info/METADATA
nocturne-0.0.6.dist-info/WHEEL
nocturne-0.0.6.dist-info/top_level.txt
nocturne-0.0.6.dist-info/RECORD
