Metadata-Version: 2.1
Name: nocturne
Version: 0.0.6
Summary: Nocturne - utilities for Scalable Deep Learning with Spark, Horovod and Petastorm
Author: Ivan Trusov
License: UNKNOWN
Platform: UNKNOWN
Classifier: Intended Audience :: Developers
